shortestpaths/__init__.py
shortestpaths/__main__.py
shortestpaths/api.py
shortestpaths/core.py
shortestpaths/dijkstra.py
shortestpaths/graph.py
shortestpaths/io.py
shortestpaths/post.py
shortestpaths/priorityq.py
shortestpaths/priorityq_test.py
shortestpaths/shortestpaths_test.py
shortestpaths/utils.py
shortestpaths/yen.py
shortestpaths-1.1.3.dist-info/COPYING
shortestpaths-1.1.3.dist-info/METADATA
shortestpaths-1.1.3.dist-info/WHEEL
shortestpaths-1.1.3.dist-info/entry_points.txt
shortestpaths-1.1.3.dist-info/top_level.txt
shortestpaths-1.1.3.dist-info/RECORD
