Metadata-Version: 2.1
Name: shortestpaths
Version: 1.1.3
Summary: Bidirectional replacement paths and k-shortest paths search with dynamic programming
Home-page: https://github.com/ThanasisMattas/shortestpaths.git
Author: Athanasios Mattas
Author-email: thanasismatt@gmail.gr
License: GNU GPL3
Platform: UNKNOWN
Classifier: Programming Language :: Python :: 3
Classifier: Natural Language :: English
Classifier: License :: OSI Approved :: GNU Lesser General Public License v3 or later (LGPLv3+)
Classifier: Operating System :: OS Independent
Requires-Dist: click (>=7.1.2)
Requires-Dist: numpy (>=1.19.2)
Requires-Dist: matplotlib (>=3.3.2)
Requires-Dist: scipy (>=1.6.1)
Requires-Dist: networkx (>=2.5)
Provides-Extra: profiling
Requires-Dist: scikit-learn (>=0.24.2) ; extra == 'profiling'
Provides-Extra: testing
Requires-Dist: pytest (>=6.1.1) ; extra == 'testing'
